openapitools/__init__.py
openapitools/builders.py
openapitools/definitions.py
openapitools/helpers.py
openapitools/types.py
openapitools-0.0.2.dist-info/METADATA
openapitools-0.0.2.dist-info/RECORD
openapitools-0.0.2.dist-info/WHEEL
openapitools-0.0.2.dist-info/top_level.txt
tests/__init__.py
tests/test_schema.py
