Metadata-Version: 2.1
Name: openapitools
Version: 0.0.2
Summary: OpenAPI v3 Object Model and Helpers
Home-page: https://github.com/zloyuser/openapi-tools
Author: Anton Shabouta
Author-email: zloyusr@gmail.com
License: UNKNOWN
Platform: UNKNOWN
Classifier: Programming Language :: Python :: 3
Classifier: License :: OSI Approved :: MIT License
Classifier: Operating System :: OS Independent
